{
	"format_version": "1.12.0",
	"minecraft:geometry": [
		{
			"description": {
				"identifier": "geometry.unknown",
				"texture_width": 16,
				"texture_height": 16,
				"visible_bounds_width": 3,
				"visible_bounds_height": 2.5,
				"visible_bounds_offset": [0, 0.75, 0]
			},
			"bones": [
				{
					"name": "bb_main",
					"pivot": [0, 0, 0],
					"cubes": [
						{"origin": [-8, 0, -8], "size": [16, 6, 16], "uv": [0, 0]}
					]
				},
				{
					"name": "group",
					"pivot": [0, 7, 15],
					"cubes": [
						{"origin": [5, 6, 5], "size": [2.98, 3, 3], "uv": [22, 28]},
						{"origin": [5, 6, 4], "size": [2.98, 2, 1], "uv": [44, 29]},
						{"origin": [5.01, 1.8, -5.05], "size": [2.98, 1, 5], "pivot": [8, 12, -5], "rotation": [45, 0, 0], "uv": [0, 6]},
						{"origin": [4.0437, -0.40876, 5], "size": [1, 5, 2.98], "pivot": [9.84368, 5.64124, -4.99], "rotation": [0, 0, 45], "uv": [28, 37]},
						{"origin": [5, 6, 3], "size": [2.98, 1, 1], "uv": [7, 45]},
						{"origin": [4, 6, 5.02], "size": [1, 2, 2.98], "uv": [8, 41]},
						{"origin": [3, 6, 5.02], "size": [1, 1, 2.98], "uv": [43, 32]},
						{"origin": [5, 6, 4], "size": [2.98, 2, 1], "uv": [44, 22]},
						{"origin": [5, 6, 3], "size": [2.98, 1, 1], "uv": [44, 39]}
					]
				},
				{
					"name": "group2",
					"pivot": [0, 7, 15],
					"cubes": [
						{"origin": [-8, 6, 5], "size": [3, 3, 2.98], "uv": [30, 32]},
						{"origin": [-4, 6, 5], "size": [1, 1, 2.98], "uv": [43, 26]},
						{"origin": [-8, 6, 4], "size": [2.98, 2, 1], "uv": [19, 44]},
						{"origin": [-8, 6, 3], "size": [2.98, 1, 1], "uv": [39, 44]},
						{"origin": [-5, 6, 5], "size": [1, 2, 2.98], "uv": [40, 40]},
						{"origin": [-8.04911, 5.71475, 5], "size": [5, 1, 2.98], "pivot": [-3.76601, 4.17678, 6.39], "rotation": [0, 0, 45], "uv": [0, 12]},
						{"origin": [-8, 6.45441, 5.11714], "size": [2.98, 1, 5], "pivot": [-2.62, 2.05027, 5.69288], "rotation": [45, 0, 0], "uv": [0, 0]}
					]
				},
				{
					"name": "group3",
					"pivot": [-8, 8, 8],
					"cubes": [
						{"origin": [-7.98, 6, -5], "size": [2.98, 2, 1], "uv": [33, 43]},
						{"origin": [-7.98, 6, -8], "size": [2.98, 3, 3], "uv": [22, 22]},
						{"origin": [-7.98, 6, -4], "size": [2.98, 1, 1], "uv": [44, 37]},
						{"origin": [-5, 6, -8], "size": [1, 2, 2.98], "uv": [32, 22]},
						{"origin": [-4, 6, -8], "size": [1, 1, 2.98], "uv": [12, 43]},
						{"origin": [-7.98, 8.75318, 0.66691], "size": [2.98, 5, 1], "pivot": [-2.6, 3.32892, 4.07105], "rotation": [45, 0, 0], "uv": [38, 22]},
						{"origin": [0.66691, 8.75318, -8], "size": [1, 5, 2.98], "pivot": [4.07105, 3.32892, -10.4], "rotation": [0, 0, -45], "uv": [22, 34]}
					]
				},
				{
					"name": "group4",
					"pivot": [-8, 8, 8],
					"cubes": [
						{"origin": [4, 6, -7.98], "size": [1, 2, 2.98], "uv": [9, 6]},
						{"origin": [5, 6, -7.98], "size": [3, 3, 2.98], "uv": [30, 26]},
						{"origin": [3, 6, -7.98], "size": [1, 1, 2.98], "uv": [24, 42]},
						{"origin": [5.02, 6, -5], "size": [2.98, 2, 1], "uv": [20, 41]},
						{"origin": [5.02, 6, -4], "size": [2.98, 1, 1], "uv": [44, 35]},
						{"origin": [-3.36812, 4.6461, -7.98], "size": [1, 5, 2.98], "pivot": [0.03603, -0.77816, -10.38], "rotation": [0, 0, 45], "uv": [16, 32]},
						{"origin": [5.02, 8.75318, 0.66691], "size": [2.98, 5, 1], "pivot": [10.4, 3.32892, 4.07105], "rotation": [45, 0, 0], "uv": [34, 37]}
					]
				}
			]
		}
	]
}