{
  "variants": {
    "facing=down": {
      "model": "industrizer:block/assembler"
    },
    "facing=up": {
      "model": "industrizer:block/assembler"
    },
    "facing=north": {
      "model": "industrizer:block/assembler"
    },
    "facing=south": {
      "model": "industrizer:block/assembler",
      "y": 180
    },
    "facing=west": {
      "model": "industrizer:block/assembler",
      "y": 270
    },
    "facing=east": {
      "model": "industrizer:block/assembler",
      "y": 90
    }
  }
}